{
    "AX": {
        "error": 0.009193004840864086,
        "error_type": "SEM",
        "filter_outliers_dict": {
            "filter_outliers": true,
            "iterations": 1,
            "std_devs": 3,
            "use_iqr_filtering": false,
            "use_standard_deviation_filtering": false
        },
        "fit": "average",
        "fn": 30,
        "include_baseline_error": true,
        "n": 30,
        "outlier_excluded": [],
        "reviewed": true,
        "user_excluded": [],
        "value": 0.03373205554671586
    },
    "CDD": {
        "error": 1.4234260015683754e-05,
        "error_type": "SEM",
        "filter_outliers_dict": {
            "filter_outliers": true,
            "iterations": 1,
            "std_devs": 10
        },
        "fit": "average",
        "value": 3.609406499945553e-05
    },
    "H1": {
        "error": 0.007860103640236434,
        "error_type": "SEM",
        "filter_outliers_dict": {
            "filter_outliers": true,
            "iterations": 1,
            "std_devs": 3,
            "use_iqr_filtering": false,
            "use_standard_deviation_filtering": false
        },
        "fit": "average",
        "fn": 30,
        "include_baseline_error": true,
        "n": 30,
        "outlier_excluded": [],
        "reviewed": true,
        "user_excluded": [],
        "value": 0.02412994302576408
    },
    "H2": {
        "error": 0.05706220866517666,
        "error_type": "SEM",
        "filter_outliers_dict": {
            "filter_outliers": true,
            "iterations": 1,
            "std_devs": 2
        },
        "fit": "average",
        "value": -0.20459085536700172
    },
    "L1": {
        "error": 0.005457454596534431,
        "error_type": "SEM",
        "filter_outliers_dict": {
            "filter_outliers": true,
            "iterations": 1,
            "std_devs": 3,
            "use_iqr_filtering": false,
            "use_standard_deviation_filtering": false
        },
        "fit": "average",
        "fn": 30,
        "include_baseline_error": true,
        "n": 30,
        "outlier_excluded": [],
        "reviewed": true,
        "user_excluded": [],
        "value": 0.04389471292185287
    },
    "L2": {
        "error": 0.004185317254889657,
        "error_type": "SEM",
        "filter_outliers_dict": {
            "filter_outliers": true,
            "iterations": 1,
            "std_devs": 2
        },
        "fit": "average",
        "value": -0.0383141991209317
    }
}